LICENSE
README.md
setup.py
ybw/__init__.py
ybw/index.py
ybw.egg-info/PKG-INFO
ybw.egg-info/SOURCES.txt
ybw.egg-info/dependency_links.txt
ybw.egg-info/entry_points.txt
ybw.egg-info/top_level.txt