Metadata-Version: 2.1
Name: ybw
Version: 0.1.1
Summary: ybw
Author: detailyang
Author-email: detailyang@gmail.com
License: MIT License
Keywords: ybw detailyang
Platform: any
License-File: LICENSE
